setup.py
randpass/__init__.py
randpass.egg-info/PKG-INFO
randpass.egg-info/SOURCES.txt
randpass.egg-info/dependency_links.txt
randpass.egg-info/entry_points.txt
randpass.egg-info/top_level.txt