Metadata-Version: 1.0
Name: randpass
Version: 1.0.2
Summary: Create a random password that is memorable to humans
Home-page: http://cct.lsu.edu/~sbrandt/
Author: Steven R. Brandt
Author-email: steven@stevenrbrandt.com
License: LGPL
Platform: UNKNOWN
